[ {
  "team_id" : 785,
  "team_name" : "Croatia",
  "lineup" : [ {
    "player_id" : 3441,
    "player_name" : "Nikola Vlašić",
    "player_nickname" : null,
    "jersey_number" : 13,
    "country" : {
      "id" : 56,
      "name" : "Croatia"
    }
  }, {
    "player_id" : 3471,
    "player_name" : "Dejan Lovren",
    "player_nickname" : null,
    "jersey_number" : 6,
    "country" : {
      "id" : 56,
      "name" : "Croatia"
    }
  }, {
    "player_id" : 5456,
    "player_name" : "Mateo Kovačić",
    "player_nickname" : null,
    "jersey_number" : 8,
    "country" : {
      "id" : 56,
      "name" : "Croatia"
    }
  }, {
    "player_id" : 5460,
    "player_name" : "Andrej Kramarić",
    "player_nickname" : null,
    "jersey_number" : 9,
    "country" : {
      "id" : 56,
      "name" : "Croatia"
    }
  }, {
    "player_id" : 5461,
    "player_name" : "Šime Vrsaljko",
    "player_nickname" : null,
    "jersey_number" : 2,
    "country" : {
      "id" : 56,
      "name" : "Croatia"
    }
  }, {
    "player_id" : 5463,
    "player_name" : "Luka Modrić",
    "player_nickname" : null,
    "jersey_number" : 10,
    "country" : {
      "id" : 56,
      "name" : "Croatia"
    }
  }, {
    "player_id" : 5465,
    "player_name" : "Ante Rebić",
    "player_nickname" : null,
    "jersey_number" : 17,
    "country" : {
      "id" : 56,
      "name" : "Croatia"
    }
  }, {
    "player_id" : 5468,
    "player_name" : "Domagoj Vida",
    "player_nickname" : null,
    "jersey_number" : 21,
    "country" : {
      "id" : 56,
      "name" : "Croatia"
    }
  }, {
    "player_id" : 5469,
    "player_name" : "Marcelo Brozović",
    "player_nickname" : null,
    "jersey_number" : 11,
    "country" : {
      "id" : 56,
      "name" : "Croatia"
    }
  }, {
    "player_id" : 5474,
    "player_name" : "Ivan Perišić",
    "player_nickname" : null,
    "jersey_number" : 4,
    "country" : {
      "id" : 56,
      "name" : "Croatia"
    }
  }, {
    "player_id" : 6305,
    "player_name" : "Milan Badelj",
    "player_nickname" : null,
    "jersey_number" : 19,
    "country" : {
      "id" : 56,
      "name" : "Croatia"
    }
  }, {
    "player_id" : 6307,
    "player_name" : "Duje Ćaleta-Car",
    "player_nickname" : null,
    "jersey_number" : 5,
    "country" : {
      "id" : 56,
      "name" : "Croatia"
    }
  }, {
    "player_id" : 6311,
    "player_name" : "Lovre Kalinić",
    "player_nickname" : null,
    "jersey_number" : 12,
    "country" : {
      "id" : 56,
      "name" : "Croatia"
    }
  }, {
    "player_id" : 7693,
    "player_name" : "Bruno Petković",
    "player_nickname" : null,
    "jersey_number" : 20,
    "country" : {
      "id" : 56,
      "name" : "Croatia"
    }
  }, {
    "player_id" : 8654,
    "player_name" : "Ante Budimir",
    "player_nickname" : null,
    "jersey_number" : 14,
    "country" : {
      "id" : 56,
      "name" : "Croatia"
    }
  }, {
    "player_id" : 8946,
    "player_name" : "Josip Brekalo",
    "player_nickname" : null,
    "jersey_number" : 7,
    "country" : {
      "id" : 56,
      "name" : "Croatia"
    }
  }, {
    "player_id" : 11127,
    "player_name" : "Borna Barišić",
    "player_nickname" : null,
    "jersey_number" : 3,
    "country" : {
      "id" : 56,
      "name" : "Croatia"
    }
  }, {
    "player_id" : 11603,
    "player_name" : "Mario Pašalić",
    "player_nickname" : null,
    "jersey_number" : 15,
    "country" : {
      "id" : 56,
      "name" : "Croatia"
    }
  }, {
    "player_id" : 16531,
    "player_name" : "Dominik Livaković",
    "player_nickname" : null,
    "jersey_number" : 1,
    "country" : {
      "id" : 56,
      "name" : "Croatia"
    }
  }, {
    "player_id" : 28368,
    "player_name" : "Luka Ivanušec",
    "player_nickname" : null,
    "jersey_number" : 26,
    "country" : {
      "id" : 56,
      "name" : "Croatia"
    }
  }, {
    "player_id" : 29163,
    "player_name" : "Josip Juranović",
    "player_nickname" : null,
    "jersey_number" : 22,
    "country" : {
      "id" : 56,
      "name" : "Croatia"
    }
  }, {
    "player_id" : 29319,
    "player_name" : "Simon Sluga",
    "player_nickname" : null,
    "jersey_number" : 23,
    "country" : {
      "id" : 56,
      "name" : "Croatia"
    }
  }, {
    "player_id" : 33018,
    "player_name" : "Joško Gvardiol",
    "player_nickname" : null,
    "jersey_number" : 25,
    "country" : {
      "id" : 56,
      "name" : "Croatia"
    }
  } ]
}, {
  "team_id" : 942,
  "team_name" : "Scotland",
  "lineup" : [ {
    "player_id" : 3581,
    "player_name" : "Ryan Fraser",
    "player_nickname" : null,
    "jersey_number" : 20,
    "country" : {
      "id" : 201,
      "name" : "Scotland"
    }
  }, {
    "player_id" : 3620,
    "player_name" : "Scott McTominay",
    "player_nickname" : null,
    "jersey_number" : 4,
    "country" : {
      "id" : 201,
      "name" : "Scotland"
    }
  }, {
    "player_id" : 3655,
    "player_name" : "Andrew Robertson",
    "player_nickname" : null,
    "jersey_number" : 3,
    "country" : {
      "id" : 201,
      "name" : "Scotland"
    }
  }, {
    "player_id" : 4563,
    "player_name" : "John Fleck",
    "player_nickname" : null,
    "jersey_number" : 14,
    "country" : {
      "id" : 201,
      "name" : "Scotland"
    }
  }, {
    "player_id" : 9048,
    "player_name" : "Stephen O\"Donnell",
    "player_nickname" : "Stephen O'Donnell",
    "jersey_number" : 2,
    "country" : {
      "id" : 201,
      "name" : "Scotland"
    }
  }, {
    "player_id" : 9466,
    "player_name" : "Che Adams",
    "player_nickname" : null,
    "jersey_number" : 10,
    "country" : {
      "id" : 201,
      "name" : "Scotland"
    }
  }, {
    "player_id" : 9481,
    "player_name" : "Grant Hanley",
    "player_nickname" : null,
    "jersey_number" : 5,
    "country" : {
      "id" : 201,
      "name" : "Scotland"
    }
  }, {
    "player_id" : 9621,
    "player_name" : "Liam Cooper",
    "player_nickname" : null,
    "jersey_number" : 16,
    "country" : {
      "id" : 201,
      "name" : "Scotland"
    }
  }, {
    "player_id" : 9645,
    "player_name" : "David Marshall",
    "player_nickname" : null,
    "jersey_number" : 1,
    "country" : {
      "id" : 201,
      "name" : "Scotland"
    }
  }, {
    "player_id" : 9974,
    "player_name" : "John McGinn",
    "player_nickname" : null,
    "jersey_number" : 7,
    "country" : {
      "id" : 201,
      "name" : "Scotland"
    }
  }, {
    "player_id" : 10002,
    "player_name" : "Scott McKenna",
    "player_nickname" : null,
    "jersey_number" : 26,
    "country" : {
      "id" : 201,
      "name" : "Scotland"
    }
  }, {
    "player_id" : 10285,
    "player_name" : "Stuart Armstrong",
    "player_nickname" : null,
    "jersey_number" : 17,
    "country" : {
      "id" : 201,
      "name" : "Scotland"
    }
  }, {
    "player_id" : 10526,
    "player_name" : "Craig Gordon",
    "player_nickname" : null,
    "jersey_number" : 12,
    "country" : {
      "id" : 201,
      "name" : "Scotland"
    }
  }, {
    "player_id" : 10534,
    "player_name" : "Callum William McGregor",
    "player_nickname" : null,
    "jersey_number" : 8,
    "country" : {
      "id" : 201,
      "name" : "Scotland"
    }
  }, {
    "player_id" : 10535,
    "player_name" : "Declan Gallagher",
    "player_nickname" : null,
    "jersey_number" : 15,
    "country" : {
      "id" : 201,
      "name" : "Scotland"
    }
  }, {
    "player_id" : 10536,
    "player_name" : "James Forrest",
    "player_nickname" : null,
    "jersey_number" : 25,
    "country" : {
      "id" : 201,
      "name" : "Scotland"
    }
  }, {
    "player_id" : 10540,
    "player_name" : "Kieran Tierney",
    "player_nickname" : null,
    "jersey_number" : 6,
    "country" : {
      "id" : 201,
      "name" : "Scotland"
    }
  }, {
    "player_id" : 10774,
    "player_name" : "Jon McLaughlin",
    "player_nickname" : null,
    "jersey_number" : 21,
    "country" : {
      "id" : 201,
      "name" : "Scotland"
    }
  }, {
    "player_id" : 12510,
    "player_name" : "Ryan Christie",
    "player_nickname" : null,
    "jersey_number" : 11,
    "country" : {
      "id" : 201,
      "name" : "Scotland"
    }
  }, {
    "player_id" : 17694,
    "player_name" : "David Turnbull",
    "player_nickname" : null,
    "jersey_number" : 18,
    "country" : {
      "id" : 201,
      "name" : "Scotland"
    }
  }, {
    "player_id" : 29571,
    "player_name" : "Lyndon Dykes",
    "player_nickname" : null,
    "jersey_number" : 9,
    "country" : {
      "id" : 201,
      "name" : "Scotland"
    }
  }, {
    "player_id" : 37338,
    "player_name" : "Nathan Patterson",
    "player_nickname" : null,
    "jersey_number" : 22,
    "country" : {
      "id" : 201,
      "name" : "Scotland"
    }
  }, {
    "player_id" : 43563,
    "player_name" : "Kevin Nisbet",
    "player_nickname" : null,
    "jersey_number" : 19,
    "country" : {
      "id" : 201,
      "name" : "Scotland"
    }
  } ]
} ]